[
  {
    "inputs": [],
    "name": "BorrowNotExpired",
    "type": "error"
  },
  {
    "inputs": [],
    "name": "InsufficientDonationBalance",
    "type": "error"
  },
  {
    "inputs": [],
    "name": "InsufficientFunds",
    "type": "error"
  },
  {
    "inputs": [],
    "name": "InvalidAmount",
    "type": "error"
  },
  {
    "inputs": [],
    "name": "InvalidCoveragePercentage",
    "type": "error"
  },
  {
    "inputs": [],
    "name": "LoanNotAvailable",
    "type": "error"
  },
  {
    "inputs": [],
    "name": "MinimumDonationRequired",
    "type": "error"
  },
  {
    "inputs": [],
    "name": "NoActiveBorrowing",
    "type": "error"
  },
  {
    "inputs": [],
    "name": "OverCoverage",
    "type": "error"
  },
  {
    "inputs": [],
    "name": "RepaymentExceedsBorrowed",
    "type": "error"
  },
  {
    "anonymous": false,
    "inputs": [
      {
        "indexed": false,
        "internalType": "uint256",
        "name": "total",
        "type": "uint256"
      }
    ],
    "name": "AvailableBalanceUpdated",
    "type": "event"
  },
  {
    "anonymous": false,
    "inputs": [
      {
        "indexed": true,
        "internalType": "address",
        "name": "borrower",
        "type": "address"
      }
    ],
    "name": "BorrowLimitReached",
    "type": "event"
  },
  {
    "anonymous": false,
    "inputs": [
      {
        "indexed": true,
        "internalType": "address",
        "name": "borrower",
        "type": "address"
      },
      {
        "indexed": false,
        "internalType": "uint256",
        "name": "amount",
        "type": "uint256"
      },
      {
        "indexed": false,
        "internalType": "uint256",
        "name": "totalBorrowing",
        "type": "uint256"
      }
    ],
    "name": "Borrowed",
    "type": "event"
  },
  {
    "anonymous": false,
    "inputs": [
      {
        "indexed": true,
        "internalType": "address",
        "name": "donor",
        "type": "address"
      },
      {
        "indexed": false,
        "internalType": "uint256",
        "name": "amount",
        "type": "uint256"
      },
      {
        "indexed": false,
        "internalType": "uint256",
        "name": "totalDonation",
        "type": "uint256"
      }
    ],
    "name": "Donated",
    "type": "event"
  },
  {
    "anonymous": false,
    "inputs": [
      {
        "indexed": true,
        "internalType": "uint256",
        "name": "requisitionId",
        "type": "uint256"
      },
      {
        "indexed": true,
        "internalType": "address",
        "name": "lender",
        "type": "address"
      },
      {
        "indexed": false,
        "internalType": "uint256",
        "name": "coverageAmount",
        "type": "uint256"
      }
    ],
    "name": "LoanCovered",
    "type": "event"
  },
  {
    "anonymous": false,
    "inputs": [
      {
        "indexed": true,
        "internalType": "uint256",
        "name": "requisitionId",
        "type": "uint256"
      }
    ],
    "name": "LoanFunded",
    "type": "event"
  },
  {
    "anonymous": false,
    "inputs": [
      {
        "indexed": true,
        "internalType": "uint256",
        "name": "requisitionId",
        "type": "uint256"
      },
      {
        "indexed": true,
        "internalType": "address",
        "name": "borrower",
        "type": "address"
      },
      {
        "indexed": false,
        "internalType": "uint256",
        "name": "amount",
        "type": "uint256"
      }
    ],
    "name": "LoanRequisitionCreated",
    "type": "event"
  },
  {
    "anonymous": false,
    "inputs": [
      {
        "indexed": true,
        "internalType": "address",
        "name": "borrower",
        "type": "address"
      }
    ],
    "name": "NewBorrower",
    "type": "event"
  },
  {
    "anonymous": false,
    "inputs": [
      {
        "indexed": true,
        "internalType": "address",
        "name": "donor",
        "type": "address"
      }
    ],
    "name": "NewDonor",
    "type": "event"
  },
  {
    "anonymous": false,
    "inputs": [
      {
        "indexed": true,
        "internalType": "address",
        "name": "borrower",
        "type": "address"
      },
      {
        "indexed": false,
        "internalType": "uint256",
        "name": "amount",
        "type": "uint256"
      },
      {
        "indexed": false,
        "internalType": "uint256",
        "name": "remainingDebt",
        "type": "uint256"
      }
    ],
    "name": "Repaid",
    "type": "event"
  },
  {
    "anonymous": false,
    "inputs": [
      {
        "indexed": false,
        "internalType": "uint256",
        "name": "total",
        "type": "uint256"
      }
    ],
    "name": "TotalBorrowedUpdated",
    "type": "event"
  },
  {
    "anonymous": false,
    "inputs": [
      {
        "indexed": false,
        "internalType": "uint256",
        "name": "total",
        "type": "uint256"
      }
    ],
    "name": "TotalDonationsUpdated",
    "type": "event"
  },
  {
    "inputs": [
      {
        "internalType": "uint256",
        "name": "_amount",
        "type": "uint256"
      }
    ],
    "name": "borrow",
    "outputs": [],
    "stateMutability": "nonpayable",
    "type": "function"
  },
  {
    "inputs": [
      {
        "internalType": "address",
        "name": "",
        "type": "address"
      },
      {
        "internalType": "uint256",
        "name": "",
        "type": "uint256"
      }
    ],
    "name": "borrowerRequisitions",
    "outputs": [
      {
        "internalType": "uint256",
        "name": "",
        "type": "uint256"
      }
    ],
    "stateMutability": "view",
    "type": "function"
  },
  {
    "inputs": [
      {
        "internalType": "address",
        "name": "_user",
        "type": "address"
      },
      {
        "internalType": "uint256",
        "name": "_amount",
        "type": "uint256"
      }
    ],
    "name": "canUserBorrow",
    "outputs": [
      {
        "internalType": "bool",
        "name": "",
        "type": "bool"
      }
    ],
    "stateMutability": "view",
    "type": "function"
  },
  {
    "inputs": [
      {
        "internalType": "uint256",
        "name": "requisitionId",
        "type": "uint256"
      },
      {
        "internalType": "uint32",
        "name": "coveragePercentage",
        "type": "uint32"
      }
    ],
    "name": "coverLoan",
    "outputs": [],
    "stateMutability": "nonpayable",
    "type": "function"
  },
  {
    "inputs": [
      {
        "internalType": "uint256",
        "name": "_amount",
        "type": "uint256"
      },
      {
        "internalType": "uint32",
        "name": "_minimumCoverage",
        "type": "uint32"
      },
      {
        "internalType": "uint256",
        "name": "_durationDays",
        "type": "uint256"
      }
    ],
    "name": "createLoanRequisition",
    "outputs": [
      {
        "internalType": "uint256",
        "name": "",
        "type": "uint256"
      }
    ],
    "stateMutability": "nonpayable",
    "type": "function"
  },
  {
    "inputs": [],
    "name": "donate",
    "outputs": [],
    "stateMutability": "payable",
    "type": "function"
  },
  {
    "inputs": [],
    "name": "getAvailableBalance",
    "outputs": [
      {
        "internalType": "uint256",
        "name": "",
        "type": "uint256"
      }
    ],
    "stateMutability": "view",
    "type": "function"
  },
  {
    "inputs": [],
    "name": "getAvailableBorrowAmount",
    "outputs": [
      {
        "internalType": "uint256",
        "name": "",
        "type": "uint256"
      }
    ],
    "stateMutability": "view",
    "type": "function"
  },
  {
    "inputs": [
      {
        "internalType": "address",
        "name": "borrower",
        "type": "address"
      }
    ],
    "name": "getBorrowerRequisitions",
    "outputs": [
      {
        "internalType": "uint256[]",
        "name": "",
        "type": "uint256[]"
      }
    ],
    "stateMutability": "view",
    "type": "function"
  },
  {
    "inputs": [
      {
        "internalType": "address",
        "name": "_user",
        "type": "address"
      }
    ],
    "name": "getBorrowing",
    "outputs": [
      {
        "internalType": "uint256",
        "name": "",
        "type": "uint256"
      }
    ],
    "stateMutability": "view",
    "type": "function"
  },
  {
    "inputs": [],
    "name": "getContractBalance",
    "outputs": [
      {
        "internalType": "uint256",
        "name": "",
        "type": "uint256"
      }
    ],
    "stateMutability": "view",
    "type": "function"
  },
  {
    "inputs": [
      {
        "internalType": "uint256",
        "name": "requisitionId",
        "type": "uint256"
      }
    ],
    "name": "getCoveringLenders",
    "outputs": [
      {
        "internalType": "address[]",
        "name": "",
        "type": "address[]"
      }
    ],
    "stateMutability": "view",
    "type": "function"
  },
  {
    "inputs": [
      {
        "internalType": "address",
        "name": "_user",
        "type": "address"
      }
    ],
    "name": "getDonation",
    "outputs": [
      {
        "internalType": "uint256",
        "name": "",
        "type": "uint256"
      }
    ],
    "stateMutability": "view",
    "type": "function"
  },
  {
    "inputs": [
      {
        "internalType": "address",
        "name": "_user",
        "type": "address"
      }
    ],
    "name": "getLastBorrowTime",
    "outputs": [
      {
        "internalType": "uint256",
        "name": "",
        "type": "uint256"
      }
    ],
    "stateMutability": "view",
    "type": "function"
  },
  {
    "inputs": [
      {
        "internalType": "uint256",
        "name": "requisitionId",
        "type": "uint256"
      },
      {
        "internalType": "address",
        "name": "lender",
        "type": "address"
      }
    ],
    "name": "getLenderCoverage",
    "outputs": [
      {
        "internalType": "uint256",
        "name": "",
        "type": "uint256"
      }
    ],
    "stateMutability": "view",
    "type": "function"
  },
  {
    "inputs": [
      {
        "internalType": "uint256",
        "name": "requisitionId",
        "type": "uint256"
      }
    ],
    "name": "getRequisitionInfo",
    "outputs": [
      {
        "components": [
          {
            "internalType": "address",
            "name": "borrower",
            "type": "address"
          },
          {
            "internalType": "uint256",
            "name": "amount",
            "type": "uint256"
          },
          {
            "internalType": "uint32",
            "name": "minimumCoverage",
            "type": "uint32"
          },
          {
            "internalType": "uint32",
            "name": "currentCoverage",
            "type": "uint32"
          },
          {
            "internalType": "enum ILoanMachine.BorrowStatus",
            "name": "status",
            "type": "uint8"
          },
          {
            "internalType": "uint256",
            "name": "durationDays",
            "type": "uint256"
          },
          {
            "internalType": "uint256",
            "name": "creationTime",
            "type": "uint256"
          },
          {
            "internalType": "uint256",
            "name": "coveringLendersCount",
            "type": "uint256"
          }
        ],
        "internalType": "struct ILoanMachine.RequisitionInfo",
        "name": "",
        "type": "tuple"
      }
    ],
    "stateMutability": "view",
    "type": "function"
  },
  {
    "inputs": [],
    "name": "getTotalBorrowed",
    "outputs": [
      {
        "internalType": "uint256",
        "name": "",
        "type": "uint256"
      }
    ],
    "stateMutability": "view",
    "type": "function"
  },
  {
    "inputs": [],
    "name": "getTotalDonations",
    "outputs": [
      {
        "internalType": "uint256",
        "name": "",
        "type": "uint256"
      }
    ],
    "stateMutability": "view",
    "type": "function"
  },
  {
    "inputs": [],
    "name": "repay",
    "outputs": [],
    "stateMutability": "payable",
    "type": "function"
  },
  {
    "inputs": [],
    "name": "requisitionCounter",
    "outputs": [
      {
        "internalType": "uint256",
        "name": "",
        "type": "uint256"
      }
    ],
    "stateMutability": "view",
    "type": "function"
  }
]