[
  {
    "anonymous": false,
    "inputs": [
      {
        "indexed": true,
        "internalType": "address",
        "name": "borrower",
        "type": "address"
      },
      {
        "indexed": false,
        "internalType": "enum DebtTracker.DebtStatus",
        "name": "newStatus",
        "type": "uint8"
      }
    ],
    "name": "BorrowerStatusUpdated",
    "type": "event"
  },
  {
    "anonymous": false,
    "inputs": [
      {
        "indexed": true,
        "internalType": "address",
        "name": "borrower",
        "type": "address"
      }
    ],
    "name": "DebtorAdded",
    "type": "event"
  },
  {
    "anonymous": false,
    "inputs": [
      {
        "indexed": true,
        "internalType": "address",
        "name": "borrower",
        "type": "address"
      }
    ],
    "name": "DebtorRemoved",
    "type": "event"
  },
  {
    "anonymous": false,
    "inputs": [
      {
        "indexed": false,
        "internalType": "uint256",
        "name": "timestamp",
        "type": "uint256"
      }
    ],
    "name": "MonthlyUpdateTriggered",
    "type": "event"
  },
  {
    "inputs": [],
    "name": "MONTHLY_INTERVAL",
    "outputs": [
      {
        "internalType": "uint256",
        "name": "",
        "type": "uint256"
      }
    ],
    "stateMutability": "view",
    "type": "function"
  }
]